odoo/addons/website_sale_hide_empty_category/README.rst
odoo/addons/website_sale_hide_empty_category/__init__.py
odoo/addons/website_sale_hide_empty_category/__manifest__.py
odoo/addons/website_sale_hide_empty_category/i18n/ca.po
odoo/addons/website_sale_hide_empty_category/i18n/es.po
odoo/addons/website_sale_hide_empty_category/i18n/fr.po
odoo/addons/website_sale_hide_empty_category/i18n/website_sale_hide_empty_category.pot
odoo/addons/website_sale_hide_empty_category/models/__init__.py
odoo/addons/website_sale_hide_empty_category/models/product_public_category.py
odoo/addons/website_sale_hide_empty_category/readme/CONTRIBUTORS.rst
odoo/addons/website_sale_hide_empty_category/readme/DESCRIPTION.rst
odoo/addons/website_sale_hide_empty_category/readme/HISTORY.rst
odoo/addons/website_sale_hide_empty_category/readme/USAGE.rst
odoo/addons/website_sale_hide_empty_category/static/description/icon.png
odoo/addons/website_sale_hide_empty_category/static/description/index.html
odoo/addons/website_sale_hide_empty_category/views/website_sale_templates.xml
odoo12_addon_website_sale_hide_empty_category-12.0.1.0.0.99.dev10.dist-info/METADATA
odoo12_addon_website_sale_hide_empty_category-12.0.1.0.0.99.dev10.dist-info/WHEEL
odoo12_addon_website_sale_hide_empty_category-12.0.1.0.0.99.dev10.dist-info/top_level.txt
odoo12_addon_website_sale_hide_empty_category-12.0.1.0.0.99.dev10.dist-info/RECORD
